hilok.cp311-win_amd64.pyd
hilok-1.3.1.dist-info/LICENSE
hilok-1.3.1.dist-info/METADATA
hilok-1.3.1.dist-info/WHEEL
hilok-1.3.1.dist-info/top_level.txt
hilok-1.3.1.dist-info/zip-safe
hilok-1.3.1.dist-info/RECORD
