Metadata-Version: 2.1
Name: hilok
Version: 1.3.1
Summary: Fast hierarchical locks
Home-page: https://github.com/AtakamaLLC/hilok
Author: Erik aronesty
Author-email: erik@atakama.com
Requires-Python: >=3.7
License-File: LICENSE
Provides-Extra: test
Requires-Dist: pytest (>=6.0) ; extra == 'test'
